{
  "active":true,
  "name":"KLAY_USD",
  "adapterId":"8b7460cccfa0aca303ee85c3fb81c344faad2fbab415adc32b2984008b7efd76",
  "oracleAddress":"0xCC4377b912c4517Fe895817c6a7c6937D92A70B3",
  "category": 2,
  "frequency": 30000000000,
  "feeds":[
    {
      "url":"https://min-api.cryptocompare.com/data/pricemultifull?fsyms=KLAY&tsyms=USD",
      "request_type":0,
      "headers":[
        {
          "field":{
            "Content-Type":"application/json"
          }
        }
      ],
      "reducers":[
        {
          "function":"PARSE",
          "args":["$.RAW.KLAY.USD.PRICE"]
        },
        {
          "function":"FLOAT64_MUL_UINT64",
          "args":[
            "1000000000"
          ]
        }
      ],
      "payload": ""
    },
    {
      "url":"https://rest.coinapi.io/v1/exchangerate/KLAY/USD",
      "request_type": 0,
      "headers":[
        {
          "field":{
            "X-CoinAPI-Key":"${X_COIN_API_KEY}"
          }
        }
      ],
      "reducers":[
        {
          "function":"PARSE",
          "args":["$.rate"]
        },
        {
          "function":"FLOAT64_MUL_UINT64",
          "args":[
            "1000000000"
          ]
        }
      ]
    }
  ]
}